{
  "contest": {
    "title": "Win ₱500 sent through GCash",
    "tagline": "React with ❤️ to our Facebook post for your chance to win",
    "description": "",
    "fbPostUrl": "https://www.facebook.com/share/12345/",
    "announcementDate": "2025-09-26T04:00:00.000Z",
    "mechanics": [
      "React with ❤️ to our Facebook post",
      "Winner will be announced on this page September 26th at 12 PM"
    ]
  },
  "winner": "Gwyneth Momo",
  "contestants": [
    "Robin Rita",
    "Shela Ni",
    "Elisa Rita Baquero",
    "Rob Rita",
    "Nena Rita Torralba",
    "Magie Bandivas",
    "Julie Ann Colwyneths",
    "Morphle Red",
    "Melissa Ducalang",
    "AgnesGac April",
    "Sandra Rojas",
    "Vilma Mabansag",
    "Keith Gabrielle",
    "Clyde Uzzil A Labrada",
    "Charelyn Samson",
    "Margs Melendres Tauy",
    "Ginalyn Samson",
    "EN Rieb",
    "Ne Ri Zza",
    "JD Aguirre Molino",
    "Harvey Brazil",
    "Regina Mae Brazil Mabini",
    "Ma Geraldin Mabini",
    "Kenneth Navarro",
    "Marife Capongcol",
    "Lorelie Galo Ripalda",
    "Ces Kenlly Mckay Mckyenll",
    "Lyn Lyn Francisco",
    "Erolyn Jocelyn",
    "Margiecaii Llavado",
    "Kurt Cedric Madera Ibañez",
    "Lynria Villarosa Peñero",
    "Alberca Jhoy",
    "Hiede Garbo",
    "Maria Josie B. Bendo",
    "Lia Jeane Lowaton",
    "Ayac Jho",
    "Jonalyn Agero",
    "Marjorie Mabansag",
    "Zi Rell",
    "Clarito Perla",
    "Noel Rarugal",
    "Ryan Rey Navarro",
    "Liezl Babon",
    "CJ Neri",
    "Vince Pasana",
    "Dazel Quiroba",
    "Marilyn Placido",
    "Evelyn Mondes",
    "Ashie Ann Fuentes",
    "Jean April A. Langcuyan",
    "Armida Rita",
    "Febrian Dasigan Gemeda",
    "Marne Abancenia Benigno",
    "Jan Cinco",
    "Gabriel Dalaguit",
    "Genelyn Mationg",
    "Itzme Thea",
    "Kulas Kablas",
    "Cesar Cinco",
    "Elaiza Lumutan",
    "Jennel Rita",
    "Maurianne T. Merida",
    "Jennifer Rita Cedillo",
    "Dioneza Zenaida",
    "Dayanara Labajo",
    "Matthew John Marlou Rita",
    "April Rose Calzita",
    "Applerose Rita Dalaguit",
    "Melanie Roble Tajor Polido",
    "Normie Matedios Canania",
    "Rezilda Dalaguit",
    "Marivic Cataag",
    "Viv Yen Babalcon Davantes",
    "Rechelle Solmeron",
    "Puffer Fish",
    "Daffny Biong Palermo",
    "Aia Jhernnie Dano",
    "Nestine Nicole Brazil Navarro",
    "Andy Regaña",
    "Anna Davantes",
    "Roderick Castulo Gula",
    "Hello Reworn",
    "Hayde Caldo",
    "Dexter Lorica",
    "Oh Kha Lee",
    "Noel Brazil",
    "Michael Job B. Navarro",
    "Gwyneth Momo",
    "Christtle Grace A. Tulabing",
    "Lalai Brazil",
    "Jallan Maramag",
    "Aileen Amos",
    "JM Mabini",
    "Annabel Gentallan",
    "Maribel Castillo",
    "Ronry Davantes",
    "Abejo Baccol Marlon",
    "Jie Brazil",
    "Ronaldreg Davantes",
    "Arreemejo Cinco Gedz",
    "Nicolette Momo",
    "Glenn Navarro",
    "Kyle Bandivas",
    "Jean Brazil",
    "Kyle Bandivas",
    "Benjamin Davantes",
    "Elma H. Cabueñas",
    "Benjo Garcia",
    "Ha'ze Llabore Perol",
    "Richella Llabore",
    "Albeza Ocale",
    "Eds Garcia-Sevilla",
    "Alona Azores",
    "Mariel Remigio",
    "Emelyn Gacho Ramos",
    "Amparo Jane Capalar",
    "Nerissa Branzuela",
    "Hacim Recillub",
    "Cristalyn Saberit Baldecanas",
    "Ivy Olaivar",
    "Settie Revilla",
    "Nhelyrose Astorga Baclea-an",
    "Rienard Dave Cajes",
    "Kenneth Apuya Obispo",
    "SisterMarian Joyce Gregas",
    "Mary Ann Escalaña"
    ]
}